{"name":"build-javascript","namedChunkGroups":{"polyfill":{"name":"polyfill","assets":[{"name":"webpack-runtime-3d5ec0b8680de3570daa.js","size":3849},{"name":"polyfill-ab2697a1c908c5f7e42f.js","size":85836}],"filteredAssets":0,"assetsSize":89685,"filteredAuxiliaryAssets":2,"auxiliaryAssetsSize":223483},"app":{"name":"app","assets":[{"name":"webpack-runtime-3d5ec0b8680de3570daa.js","size":3849},{"name":"framework-0c17c7b3e82058a58807.js","size":141375},{"name":"app-388ae77bc962cdd0787a.js","size":202003}],"filteredAssets":0,"assetsSize":347227,"filteredAuxiliaryAssets":3,"auxiliaryAssetsSize":1206395},"component---src-pages-404-tsx":{"name":"component---src-pages-404-tsx","assets":[{"name":"commons-a8d06029dd1c79ea214d.js","size":28084},{"name":"component---src-pages-404-tsx-9647d7b4441d7028a109.js","size":490}],"filteredAssets":0,"assetsSize":28574,"filteredAuxiliaryAssets":2,"auxiliaryAssetsSize":207025},"component---src-pages-index-tsx":{"name":"component---src-pages-index-tsx","assets":[{"name":"commons-a8d06029dd1c79ea214d.js","size":28084},{"name":"component---src-pages-index-tsx-7e01ad68ac374c970a61.js","size":3203}],"filteredAssets":0,"assetsSize":31287,"filteredAuxiliaryAssets":2,"auxiliaryAssetsSize":214908},"component---src-templates-generic-page-with-aside-tsx":{"name":"component---src-templates-generic-page-with-aside-tsx","assets":[{"name":"commons-a8d06029dd1c79ea214d.js","size":28084},{"name":"component---src-templates-generic-page-with-aside-tsx-91ac6dc7c9962fe67766.js","size":4241}],"filteredAssets":0,"assetsSize":32325,"filteredAuxiliaryAssets":2,"auxiliaryAssetsSize":218600}},"assetsByChunkName":{"polyfill":["webpack-runtime-3d5ec0b8680de3570daa.js","polyfill-ab2697a1c908c5f7e42f.js"],"app":["webpack-runtime-3d5ec0b8680de3570daa.js","framework-0c17c7b3e82058a58807.js","app-388ae77bc962cdd0787a.js"],"component---src-pages-404-tsx":["commons-a8d06029dd1c79ea214d.js","component---src-pages-404-tsx-9647d7b4441d7028a109.js"],"component---src-pages-index-tsx":["commons-a8d06029dd1c79ea214d.js","component---src-pages-index-tsx-7e01ad68ac374c970a61.js"],"component---src-templates-generic-page-with-aside-tsx":["commons-a8d06029dd1c79ea214d.js","component---src-templates-generic-page-with-aside-tsx-91ac6dc7c9962fe67766.js"]},"childAssetsByChunkName":{}}